[
	{
		"__TYPE__": "SharedSliceContent",
		"variation": "default",
		"primary": {
			"heading": {
				"__TYPE__": "StructuredTextContent",
				"value": [
					{
						"type": "heading2",
						"content": {
							"text": "Small"
						}
					}
				]
			},
			"body": {
				"__TYPE__": "StructuredTextContent",
				"value": [
					{
						"type": "paragraph",
						"content": {
							"text": "Minim proident qui minim enim nostrud fugiat veniam ex esse voluptate labore. Eu do duis sunt culpa culpa ullamco consectetur deserunt cupidatat quis culpa occaecat occaecat commodo."
						}
					}
				]
			},
			"product": {
				"__TYPE__": "GroupContentType",
				"value": [
					{
						"__TYPE__": "GroupItemContent",
						"value": [
							[
								"skateboard",
								{
									"key": "1749c45c-559b-45a1-b5df-ec346391222a",
									"__TYPE__": "LinkContent",
									"value": {
										"__TYPE__": "DocumentLink",
										"id": "mock_document_id"
									}
								}
							]
						]
					}
				]
			}
		},
		"items": []
	}
]